LICENSE.txt
README.md
setup.cfg
setup.py
src/mappy/__init__.py
src/mappy/class_mapper.py
src/mappy/dynamic_class_mapper.py
src/mappy/mapping_tools.py
src/mappy/model/__init__.py
src/mappy/model/trait_key_matching.py
src/mappy/model/dynamic/__init__.py
src/mappy/model/dynamic/bar.py
src/mappy/model/dynamic/foo.py
src/mappy_json_object_mapper.egg-info/PKG-INFO
src/mappy_json_object_mapper.egg-info/SOURCES.txt
src/mappy_json_object_mapper.egg-info/dependency_links.txt
src/mappy_json_object_mapper.egg-info/top_level.txt