Metadata-Version: 2.4
Name: mappy_json-object-mapper
Version: 1.0.2
Summary: MapPy Json - Object Mapper
Home-page: https://github.com/PazsitZ/mappy-json-object-mapper
Author: Zoltan Pazsit
Author-email: pazsitz@pazsitz.hu
License: MIT
Keywords: python json object mapper
License-File: LICENSE.txt
Dynamic: author
Dynamic: author-email
Dynamic: description
Dynamic: description-content-type
Dynamic: home-page
Dynamic: keywords
Dynamic: license
Dynamic: license-file
Dynamic: summary
